scrapeer_cli.py
scrapeer/__init__.py
scrapeer/config.py
scrapeer/http.py
scrapeer/scraper.py
scrapeer/udp.py
scrapeer/utils.py
scrapeer-1.0.3.dist-info/licenses/LICENSE.txt
scrapeer-1.0.3.dist-info/METADATA
scrapeer-1.0.3.dist-info/WHEEL
scrapeer-1.0.3.dist-info/entry_points.txt
scrapeer-1.0.3.dist-info/top_level.txt
scrapeer-1.0.3.dist-info/RECORD
