Metadata-Version: 2.4
Name: scrapeer
Version: 1.0.3
Summary: Essential Python library that scrapes HTTP(S) and UDP trackers for torrent information.
Author: tboy1337
License: MIT
Project-URL: Homepage, https://github.com/tboy1337/scrapeer-py
Project-URL: Download, https://github.com/tboy1337/scrapeer-py/releases/latest
Project-URL: Repository, https://github.com/tboy1337/scrapeer-py
Project-URL: Author, https://tboy1337.github.io/
Keywords: torrent,torrents,scraper,scrapeer,torrent-scraper,torrent-scraping
Classifier: Programming Language :: Python :: 3
Classifier: License :: OSI Approved :: MIT License
Classifier: Operating System :: OS Independent
Requires-Python: >=3.6
License-File: LICENSE.txt
Dynamic: license-file
